{
  "schemaVersion": 1,
  "id": "reapingmod",
  "version": "${version}",
  "name": "Reaping Mod",
  "description": "A Farming Mod",
  "authors": [
    "Jamalam360 - Owner, Developer",
    "LordDeatHunter - Artist"
  ],
  "contributors": [],
  "contact": {
    "homepage": "https://www.curseforge.com/minecraft/mc-mods/reaping-mod-fabric",
    "issues": "https://github.com/Jamalam360/ReapingFabric/issues",
    "sources": "https://github.com/Jamalam360/ReapingFabric"
  },
  "license": "MIT",
  "icon": "assets/reapingmod/icon.png",
  "environment": "*",
  "accessWidener" : "reapingmod.accesswidener",
  "entrypoints": {
    "main": [
      "com.jamalam360.ReapingModInit"
    ],
    "modmenu": [
      "com.jamalam360.config.ModMenuIntegration"
    ]
  },
  "depends": {
    "fabricloader": ">=0.11.3",
    "fabric": "*"
  }
}